super_hash/__init__.py
super_hash/instuctions.ignore.py
super_hash/__dependencies__/__init__.py
super_hash/__dependencies__/simple_namespace/main/setup.py
super_hash/__dependencies__/simple_namespace/main/simple_namespace/__init__.py
super_hash/__dependencies__/simple_namespace/main/simple_namespace/main.py
super_hash-1.4.0.dist-info/METADATA
super_hash-1.4.0.dist-info/WHEEL
super_hash-1.4.0.dist-info/top_level.txt
super_hash-1.4.0.dist-info/RECORD
