Metadata-Version: 2.1
Name: super_hash
Version: 1.4.0
Summary: hash the unhashable, hash everything
Home-page: https://github.com/jeff-hykin/super_hash.git
Author: Jeff Hykin
Author-email: jeff.hykin@gmail.com
License: MIT
Platform: UNKNOWN
Classifier: Development Status :: 5 - Production/Stable
Classifier: Intended Audience :: Developers
Classifier: Programming Language :: Python
Classifier: Programming Language :: Python :: 3
Classifier: Operating System :: OS Independent
Requires-Python: >=3.6
